[
  {
    "ref": "P1",
    "stock_initial": 100,
    "date": "2025-09-30T09:52:09.334Z"
  },
  {
    "ref": "P2",
    "stock_initial": 50,
    "date": "2025-09-30T09:52:10.327Z"
  },
  {
    "ref": "P3",
    "stock_initial": 200,
    "date": "2025-09-30T09:52:10.979Z"
  },
  {
    "ref": "P4",
    "stock_initial": 100,
    "date": "2025-09-30T09:52:11.616Z"
  },
  {
    "ref": "P5",
    "stock_initial": 150,
    "date": "2025-09-30T09:52:12.227Z"
  },
  {
    "ref": "PF1",
    "stock_initial": 45,
    "date": "2025-09-30T09:52:12.831Z"
  },
  {
    "ref": "PF2",
    "stock_initial": 68,
    "date": "2025-09-30T09:52:13.428Z"
  },
  {
    "ref": "PF3",
    "stock_initial": 34,
    "date": "2025-09-30T09:52:13.945Z"
  }
]